NumpyJichuzhishiChuyiFix1/README.md
NumpyJichuzhishiChuyiFix1/__init__.py
NumpyJichuzhishiChuyiFix1/__main__.py
NumpyJichuzhishiChuyiFix1/file.epub
NumpyJichuzhishiChuyiFix1/index.html
NumpyJichuzhishiChuyiFix1/css/__init__.py
NumpyJichuzhishiChuyiFix1/css/annotations.css
NumpyJichuzhishiChuyiFix1/css/main.css
NumpyJichuzhishiChuyiFix1/css/normalize.css
NumpyJichuzhishiChuyiFix1/css/popup.css
NumpyJichuzhishiChuyiFix1/font/__init__.py
NumpyJichuzhishiChuyiFix1/font/fontello.eot
NumpyJichuzhishiChuyiFix1/font/fontello.svg
NumpyJichuzhishiChuyiFix1/font/fontello.ttf
NumpyJichuzhishiChuyiFix1/font/fontello.woff
NumpyJichuzhishiChuyiFix1/img/__init__.py
NumpyJichuzhishiChuyiFix1/img/annotator-glyph-sprite.png
NumpyJichuzhishiChuyiFix1/img/annotator-icon-sprite.png
NumpyJichuzhishiChuyiFix1/img/apple-touch-icon.png
NumpyJichuzhishiChuyiFix1/img/cancelfullscreen.png
NumpyJichuzhishiChuyiFix1/img/close.png
NumpyJichuzhishiChuyiFix1/img/fullscreen.png
NumpyJichuzhishiChuyiFix1/img/loader.gif
NumpyJichuzhishiChuyiFix1/img/menu-icon.png
NumpyJichuzhishiChuyiFix1/img/save.png
NumpyJichuzhishiChuyiFix1/img/saved.png
NumpyJichuzhishiChuyiFix1/img/settings-s.png
NumpyJichuzhishiChuyiFix1/img/settings.png
NumpyJichuzhishiChuyiFix1/img/star.png
NumpyJichuzhishiChuyiFix1/js/__init__.py
NumpyJichuzhishiChuyiFix1/js/epub.js
NumpyJichuzhishiChuyiFix1/js/epub.min.js
NumpyJichuzhishiChuyiFix1/js/epub.min.map
NumpyJichuzhishiChuyiFix1/js/hooks.min.js
NumpyJichuzhishiChuyiFix1/js/hooks.min.map
NumpyJichuzhishiChuyiFix1/js/reader.js
NumpyJichuzhishiChuyiFix1/js/reader.js.map
NumpyJichuzhishiChuyiFix1/js/reader.min.js
NumpyJichuzhishiChuyiFix1/js/reader.min.map
NumpyJichuzhishiChuyiFix1/js/hooks/__init__.py
NumpyJichuzhishiChuyiFix1/js/hooks/extensions/__init__.py
NumpyJichuzhishiChuyiFix1/js/hooks/extensions/highlight.js
NumpyJichuzhishiChuyiFix1/js/libs/__init__.py
NumpyJichuzhishiChuyiFix1/js/libs/jquery.min.js
NumpyJichuzhishiChuyiFix1/js/libs/localforage.min.js
numpy_jichuzhishi_chuyi_fix1-2025.3.24.0.dist-info/METADATA
numpy_jichuzhishi_chuyi_fix1-2025.3.24.0.dist-info/WHEEL
numpy_jichuzhishi_chuyi_fix1-2025.3.24.0.dist-info/entry_points.txt
numpy_jichuzhishi_chuyi_fix1-2025.3.24.0.dist-info/top_level.txt
numpy_jichuzhishi_chuyi_fix1-2025.3.24.0.dist-info/RECORD
